modern_python_setup/__init__.py
modern_python_setup/console.py
modern_python_setup/wikipedia.py
modern_python_setup-0.3.0.dist-info/entry_points.txt
modern_python_setup-0.3.0.dist-info/LICENSE
modern_python_setup-0.3.0.dist-info/WHEEL
modern_python_setup-0.3.0.dist-info/METADATA
modern_python_setup-0.3.0.dist-info/RECORD
