Metadata-Version: 2.1
Name: modern-python-setup
Version: 0.3.0
Summary: The Modern Python Setup project
Home-page: https://github.com/hubplug/modern-python-setup
License: MIT
Keywords: modern,python,setup
Author: Hub Plug
Author-email: 31110528+hubplug@users.noreply.github.com
Requires-Python: >=3.7,<4.0
Classifier: License :: OSI Approved :: MIT License
Classifier: Programming Language :: Python :: 3
Classifier: Programming Language :: Python :: 3.7
Classifier: Programming Language :: Python :: 3.8
Requires-Dist: click (>=7.1.2,<8.0.0)
Requires-Dist: desert (>=2020.1.6,<2021.0.0)
Requires-Dist: importlib_metadata (>=1.7.0,<2.0.0); python_version < "3.8"
Requires-Dist: marshmallow (>=3.7.0,<4.0.0)
Requires-Dist: requests (>=2.24.0,<3.0.0)
Project-URL: Documentation, https://modern-python-setup.readthedocs.io
Project-URL: Repository, https://github.com/hubplug/modern-python-setup
